result/__init__.py
result/py.typed
result/result.py
result_test_publish_version-0.17.0.dev1.dist-info/LICENSE
result_test_publish_version-0.17.0.dev1.dist-info/METADATA
result_test_publish_version-0.17.0.dev1.dist-info/WHEEL
result_test_publish_version-0.17.0.dev1.dist-info/top_level.txt
result_test_publish_version-0.17.0.dev1.dist-info/zip-safe
result_test_publish_version-0.17.0.dev1.dist-info/RECORD
